testtest/__init__.py
testtest/using_click.py
testtest/scripts/__init__.py
testtest/scripts/init.py
testtest/scripts/using_click.py
testtest-1.8.dist-info/DESCRIPTION.rst
testtest-1.8.dist-info/METADATA
testtest-1.8.dist-info/RECORD
testtest-1.8.dist-info/WHEEL
testtest-1.8.dist-info/entry_points.txt
testtest-1.8.dist-info/metadata.json
testtest-1.8.dist-info/top_level.txt
