Metadata-Version: 2.0
Name: testtest
Version: 1.8
Summary: Testing Framework
Home-page: https://github.com/AlexMcCarroll/pypi_play
Author: Alex McCarroll
Author-email: alexandra@mccarrollhk.com
License: MIT
Platform: UNKNOWN
Requires-Dist: emoji
Requires-Dist: Click
